{"status":"ok","count":4,"pages":1,"author":{"id":1,"slug":"admin","name":"admin","first_name":"","last_name":"","nickname":"admin","url":"","description":""},"posts":[{"id":63,"type":"filho","slug":"testando123","url":"http:\/\/peppersp.com.br\/beacon\/filho\/testando123\/","status":"publish","title":"Testando123","title_plain":"Testando123","content":"","excerpt":"","date":"2016-03-23 23:40:59","modified":"2016-03-23 23:40:59","categories":[],"tags":[],"author":{"id":1,"slug":"admin","name":"admin","first_name":"","last_name":"","nickname":"admin","url":"","description":""},"comments":[],"attachments":[],"comment_count":0,"comment_status":"closed","custom_fields":{"idade":["10"],"sexo":["1"],"avatar":["1"]}},{"id":40,"type":"filho","slug":"eduarda","url":"http:\/\/peppersp.com.br\/beacon\/filho\/eduarda\/","status":"publish","title":"Eduarda","title_plain":"Eduarda","content":"","excerpt":"","date":"2016-03-04 18:49:04","modified":"2016-03-04 20:51:02","categories":[],"tags":[],"author":{"id":1,"slug":"admin","name":"admin","first_name":"","last_name":"","nickname":"admin","url":"","description":""},"comments":[],"attachments":[],"comment_count":0,"comment_status":"closed","custom_fields":{"idade":["4"],"sexo":["2"],"avatar":["ana"],"agenda_filho":["a:2:{i:0;s:2:\"21\";i:1;s:2:\"20\";}"]}},{"id":34,"type":"filho","slug":"joao-pedro","url":"http:\/\/peppersp.com.br\/beacon\/filho\/joao-pedro\/","status":"publish","title":"Jo\u00e3o Pedro","title_plain":"Jo\u00e3o Pedro","content":"","excerpt":"","date":"2016-03-04 18:48:41","modified":"2016-03-04 20:51:08","categories":[],"tags":[],"author":{"id":1,"slug":"admin","name":"admin","first_name":"","last_name":"","nickname":"admin","url":"","description":""},"comments":[],"attachments":[],"comment_count":0,"comment_status":"closed","custom_fields":{"idade":["7"],"sexo":["1"],"avatar":["maria"],"agenda_filho":["a:1:{i:0;s:2:\"19\";}"]}},{"id":38,"type":"filho","slug":"marcos-paulo","url":"http:\/\/peppersp.com.br\/beacon\/filho\/marcos-paulo\/","status":"publish","title":"Marcos Paulo","title_plain":"Marcos Paulo","content":"","excerpt":"","date":"2016-03-04 18:47:14","modified":"2016-03-04 20:51:12","categories":[],"tags":[],"author":{"id":1,"slug":"admin","name":"admin","first_name":"","last_name":"","nickname":"admin","url":"","description":""},"comments":[],"attachments":[],"comment_count":0,"comment_status":"closed","custom_fields":{"idade":["12"],"sexo":["1"],"avatar":["luiz"],"agenda_filho":["a:1:{i:0;s:2:\"20\";}"]}}]}
